pip_module_scanner/__init__.py
pip_module_scanner/__init__.pyc
pip_module_scanner/__main__.py
pip_module_scanner/exceptions.py
pip_module_scanner/exceptions.pyc
pip_module_scanner/scanner.py
pip_module_scanner/scanner.pyc
pip_module_scanner-0.6.dist-info/METADATA
pip_module_scanner-0.6.dist-info/RECORD
pip_module_scanner-0.6.dist-info/WHEEL
pip_module_scanner-0.6.dist-info/entry_points.txt
pip_module_scanner-0.6.dist-info/top_level.txt
tests/project/__init__.py
tests/project/example.py
