Metadata-Version: 2.1
Name: pip-module-scanner
Version: 0.6
Summary: Scans your Python project for all installed third party pip libraries and generates a requirements.txt based output.
Home-page: https://github.com/Paradoxis/PIP-Module-Scanner
Author: Luke Paris (Paradoxis)
Author-email: luke@paradoxis.nl
License: MIT
Platform: UNKNOWN
Classifier: License :: OSI Approved :: MIT License
Classifier: Programming Language :: Python
Classifier: Programming Language :: Python :: 3
Classifier: Programming Language :: Python :: 3.6
Classifier: Programming Language :: Python :: Implementation :: CPython
Classifier: Programming Language :: Python :: Implementation :: PyPy
Requires-Python: >=2.7.0
Provides-Extra: test
Provides-Extra: dev
Provides-Extra: dev
Requires-Dist: twine; extra == 'dev'
Provides-Extra: test
Requires-Dist: codecov; extra == 'test'
Requires-Dist: coverage; extra == 'test'
Requires-Dist: requests (==2.19.1); extra == 'test'
Requires-Dist: flask (==1.0.2); extra == 'test'
